{"johnelliott": [{"user": "IMBOLDN_KR", "id": "1130760433638490112", "timestamp": "2019-05-21 09:01:10", "text": "저지는 찢어졌지만, 나이키를 향한 마음은 변치 않았음을. #LeBronJames #르브론제임스 #JohnElliott #존엘리엇 #나이키아이콘 #나이키아이콘QS #나이키르브론8\nhttp://zpr.io/gFJ5U pic.twitter.com/uNO7X7tWPc", "likes": "0"}, {"user": "IMBOLDN_KR", "id": "1130760433638490112", "timestamp": "2019-05-21 09:01:10", "text": "저지는 찢어졌지만, 나이키를 향한 마음은 변치 않았음을. #LeBronJames #르브론제임스 #JohnElliott #존엘리엇 #나이키아이콘 #나이키아이콘QS #나이키르브론8\nhttp://zpr.io/gFJ5U pic.twitter.com/uNO7X7tWPc", "likes": "0"}]}